{"sections":{"collection-banner":{"type":"collection-banner","custom_css":["* {font-family: \"Futura PT\"; font-weight: 800; text-transform: uppercase; letter-spacing: 0.25rem;}"],"settings":{"color_scheme":"scheme-2","image_size":"auto","allow_transparent_header":true,"reveal":true,"enable_parallax":true,"show_image":false,"show_collection_title":true,"show_collection_description":false,"show_breadcrumb":false,"content_width":"lg","overlay_color":"#000000","overlay_opacity":30}},"main":{"type":"main-collection","custom_css":[".badge--custom {background: #F4FA5A; color: #1c1c1c; padding: 3px 10px;}",".collection-toolbar {box-shadow: none; \/* Remove box shadow *\/"],"settings":{"variant_collection":true,"enable_variant_grouping":true,"variant_groups":"Blau: graublau, graublau dipped, teal, teal dipped, petrol, petrol innen, taubenblau, taubenblau innen, wolkenblau, saphirblau, saphirblau innen, blau\nGrün: teal, teal dipped, türkis, türkis dipped, smaragdgrün, smaragdgrün innen\nWeiß: naturweiß, naturweiß dipped, sand, sand dipped, weiß innen, weiß, schneeweiß\nGrau: steingrau, steingrau dipped\nRosa: rosé, rosé dipped, karamell, karamell innen\nTransparent: transparent, line motiv, eye motiv","color_groups_gap":6,"color_groups_radius":0,"color_groups_padding_v":8,"color_groups_padding_h":16,"enable_color_filter":false,"filtered_colors":"Graublau, Graublau dipped, naturweiß, rosa, petrol","color_filter_title":"Filter by color:","color_swatch_size":26,"color_scheme":"scheme-2","hide_product_information":false,"products_per_page":16,"products_per_row_mobile":"2","products_size_desktop":"medium","show_grid_mode_selector":false,"horizontal_spacing_factor":0.2,"vertical_spacing_factor":0.3,"filter_layout":"drawer","quick_links_menu":"","show_sort_by":false,"show_filters":false,"show_results_count":false,"show_filter_group_name":false,"show_filter_values_count":true,"open_filters_by_default":false}}},"order":["collection-banner","main"]}